micromind/__init__.py
micromind/easy.py
micromind/experiment.py
micromind/imagej.py
micromind/memory.py
micromind/stamp.py
micromind/tmputils.py
micromind/analysis/__init__.py
micromind/analysis/analysis.py
micromind/analysis/cohort.py
micromind/analysis/dataframe.py
micromind/analysis/patch.py
micromind/analysis/procedure.py
micromind/cv/__init__.py
micromind/cv/conversion.py
micromind/cv/image.py
micromind/cv/morphology.py
micromind/cv/threshold.py
micromind/cv/old/__init__.py
micromind/cv/old/watershed.py
micromind/cv/old/__pycache__/__init__.cpython-37.pyc
micromind/cv/old/__pycache__/watershed.cpython-37.pyc
micromind/figure/__init__.py
micromind/figure/figure.py
micromind/geometry/__init__.py
micromind/geometry/line.py
micromind/geometry/vector.py
micromind/io/__init__.py
micromind/io/drive.py
micromind/io/image.py
micromind/microcell/__init__.py
micromind/microcell/cell.py
micromind/microcell/property.py
micromind/microcell/synapse.py
micromind/microcell/profile/__init__.py
micromind/microcell/profile/cell_profile.py
micromind/plotting/__init__.py
micromind/plotting/plot.py
micromind/slide/__init__.py
micromind/slide/chromogenic.py
micromind/slide/exceptions.py
micromind/slide/regions.py
micromind/slide/slides.py
micromind/slide/staining.py
micromind-1.2.9.dist-info/LICENSE
micromind-1.2.9.dist-info/METADATA
micromind-1.2.9.dist-info/WHEEL
micromind-1.2.9.dist-info/top_level.txt
micromind-1.2.9.dist-info/RECORD
