Metadata-Version: 2.1
Name: micromind
Version: 1.2.9
Summary: A short description
Home-page: UNKNOWN
Author: Kevin Cortacero
Author-email: kevin.cortacero@inserm.fr
License: MIT
Platform: UNKNOWN
Classifier: Programming Language :: Python :: 3.7
License-File: LICENSE
Requires-Dist: numpy
Requires-Dist: opencv-python
Requires-Dist: matplotlib
Requires-Dist: pandas
Requires-Dist: tifffile
Requires-Dist: czifile
Requires-Dist: openslide-python
Requires-Dist: imutils
